{"institutions": {"1306": {"name": "Bioingeniería Vetiver Chile SpA"}, "420": {"name": "Universidade Federal Da Paraiba"}, "377": {"name": "Fichtner GmbH"}, "10": {"name": "Centro Internacional de Estudios Superiores en Ciencias Agronómicas, Montpellier"}, "291": {"name": "University of Twente"}, "309": {"name": "Rhodos Asesorías y Proyectos Ltda."}, "247": {"name": "University of Arizona"}, "250": {"name": "University of British Columbia"}, "383": {"name": "Instituto Nacional del Agua (INA)"}, "178": {"name": "Universidad de Valencia"}, "313": {"name": "Energy Recovery, Inc."}, "559": {"name": "Consorcio I+D Vinos de Chile S.A."}, "320": {"name": "Doosan Heavy Industries and Construction Co. Ltd."}, "133": {"name": "Universidad de Finanzas de Moscú"}, "227": {"name": "Universidad Politécnica de Madrid"}, "42": {"name": "Instituto de Minas"}, "241": {"name": "Universidad Tecnológica Metropolitana"}, "125": {"name": "Universidad de Chile"}, "53": {"name": "McGill University"}, "39": {"name": "Instituto de Estudios Políticos de Grenoble"}, "415": {"name": "Universidad de Los Andes Colombia"}, "292": {"name": "University of Wales"}, "1290": {"name": "Sociedad Embotelladora de Los Ríos Ltda"}, "153": {"name": "Universidad de Magallanes"}, "88": {"name": "Universidad Adolfo Ibáñez"}, "111": {"name": "Universidad Complutense de Madrid"}, "570": {"name": "Centro de Estudios del Desarrollo (CED)"}, "35": {"name": "Georgia Institute of Technology"}, "473": {"name": "Emicontrols Ltd."}, "285": {"name": "University of Reading"}, "201": {"name": "Universidad Humboldt de Berlín"}, "316": {"name": "The University of Queensland"}, "501": {"name": "Enviro -Tox Services Inc."}, "471": {"name": "Corporación Centro de Ciencia y Tecnología de Antioquia"}, "532": {"name": "Waters of Patagonia"}, "1292": {"name": "Sergio Pacheco y Compañía Limitada"}, "1262": {"name": "Transporte y Comercial Tressa Limitada"}, "510": {"name": "IDE Technologies"}, "314": {"name": "Doosan Hydro Technology"}, "331": {"name": "Teck Resources Canadá"}, "264": {"name": "University of Leuven"}, "71003": {"name": "Agencia Regional de Desarrollo Productivo (ARDP)"}, "375": {"name": "Instituto Mexicano de Tecnología del Agua (IMTA)"}, "231": {"name": "Universidad Santiago de Compostela"}, "400": {"name": "Universidad Autónoma de Zacatecas"}, "171": {"name": "Universidad de Sao Paulo"}, "549": {"name": "Agua Potable Rural Región Metropolitana"}, "1311": {"name": "Ecoglobal E.I.R.L."}, "406": {"name": "Amphos 21 Group Chile"}, "490": {"name": "Comité Agua Potable Rural Chaihuin"}, "203": {"name": "Universidad Internacional de Andalucía"}, "561": {"name": "Ministerio de Agricultura"}, "540": {"name": "Asociación Latinoamericana de Hidrología Subterránea para el Desarrollo"}, "556": {"name": "BHP Billiton"}, "565": {"name": "Organización de las Naciones Unidas para la Educación, la Ciencia y la Cultura"}, "11": {"name": "Centro Internacional de Formación en Ciencias Ambientales"}, "85": {"name": "The Johns Hopkins University"}, "30": {"name": "Escuela Superior de Prospección Geológica"}, "70990": {"name": "Corporación Regional de Desarrollo Productivo de Coquimbo (CRDP)"}, "440": {"name": "Itasca S.A."}, "366": {"name": "Empresa de Servicios Sanitarios del Bío Bío"}, "161": {"name": "Universidad de Padua"}, "46": {"name": "Leiden University"}, "298": {"name": "Virginia Tech"}, "434": {"name": "JRI Ingeniería"}, "73": {"name": "Radboud University Nijmegen"}, "71": {"name": "Queen’s University Kingston"}, "412": {"name": "Servicio Geológico de Brasil"}, "466": {"name": "Autoridad Nacional del Agua"}, "70988": {"name": "Centro del Agua para Zonas Áridas de América Latina y el Caribe (CAZALAC)"}, "1276": {"name": "Minera Andes Iron Limitada"}, "218": {"name": "Universidad Nacional de San Agustín"}, "164": {"name": "Universidad de Piura"}, "196": {"name": "Universidad Federal de Paraná"}, "1256": {"name": "Organización de usuarios Canal Bío-bío"}, "45": {"name": "Kellogg Northwestern University"}, "362": {"name": "RWL Water-Nirosot"}, "1285": {"name": "Asociación de Exportadores de Frutas de Chile A.G."}, "480": {"name": "University of Louvain"}, "378": {"name": "Universidad Nacional de Cuyo"}, "2367": {"name": "Co-Work Patagonia"}, "68": {"name": "Pontificia Universidad Católica de Minas Gerais"}, "232": {"name": "Universidad Santo Tomás"}, "384": {"name": "Universidad Nacional Autónoma de México"}, "141": {"name": "Universidad de Hamburgo"}, "353": {"name": "Institut de Recherche pour le Développement (IRD)"}, "429": {"name": "Universidade Federal de Pernambuco"}, "123": {"name": "Universidad de Bremen"}, "2366": {"name": "Aldea Cowork"}, "550": {"name": "Bechtel Corporation Chile"}, "2359": {"name": "Working House"}, "230": {"name": "Universidad San Sebastián"}, "489": {"name": "Comité de Protección y Desarrollo Sustentable de Tinquilco"}, "472": {"name": "Universidade do Vale do Itajaí"}, "287": {"name": "University of Southern California"}, "255": {"name": "University of Cincinnati"}, "1267": {"name": "Esval SA"}, "541": {"name": "Superintendencia de Servicios Sanitarios"}, "405": {"name": "Geoklock"}, "424": {"name": "Independiente"}, "528": {"name": "Arcadis Chile"}, "103": {"name": "Universidad Católica de la Santísima Concepción"}, "223": {"name": "Universidad París XII Val de Marne"}, "95": {"name": "Universidad Autónoma de Baja California"}, "67": {"name": "Pontificia Universidad Católica de Chile"}, "436": {"name": "Compañía Chilena de Perforaciones"}, "418": {"name": "Universidad de Buenos Aires"}, "92": {"name": "Universidad Aristotélica de Tesalónica"}, "251": {"name": "University of California"}, "352": {"name": "CDM Smith"}, "2362": {"name": "Workingplace"}, "523": {"name": "Universidade Federal de Santa Maria (UFSM)"}, "526": {"name": "Amphos 21 Group España"}, "1236": {"name": "Mentores de Impacto"}, "488": {"name": "WWF Chile"}, "469": {"name": "Universidade Federal do Ceará (UFC)"}, "416": {"name": "Universidad Nacional Jorge Basadre Grohmann"}, "67890": {"name": "TETRA Technologies"}, "89": {"name": "Universidad Albert Ludwig, Freiburg im Breisgau"}, "281": {"name": "University of Oregon"}, "71004": {"name": "CULTIVOS HIDROBIOLOGICOS Y BIOTECNOLOGÍA AGUAMARINA S.A."}, "236": {"name": "Universidad Técnica de Dresde"}, "328": {"name": "SRK Consulting Perú"}, "505": {"name": "BHP Billiton Australia"}, "499": {"name": "Sinclair Knight Merz"}, "498": {"name": "GHD"}, "78": {"name": "Staffordshire University"}, "1243": {"name": "ME Mujeres Empresarias"}, "446": {"name": "Universidade Federal do Rio de Janeiro"}, "518": {"name": "Golder Associates Chile"}, "87": {"name": "Universidad Academia de Humanismo Cristiano"}, "279": {"name": "University of Newcastle Upon Tyne"}, "571": {"name": "Ministerio del Medio Ambiente"}, "564": {"name": "Ministerio de Obras Públicas"}, "1301": {"name": "Efizity Ingeniería SpA"}, "84": {"name": "The City University"}, "269": {"name": "University of Maryland"}, "7": {"name": "Centro de Estudios y Experimentación de Obras Públicas (CEDEX)"}, "260": {"name": "University of Idaho"}, "507": {"name": "Hatch Chile"}, "209": {"name": "Universidad Metodista de Sao Paulo"}, "520": {"name": "Anglo American Brasil"}, "128": {"name": "Universidad de Córdoba"}, "96": {"name": "Universidad Autónoma de Barcelona"}, "2363": {"name": "C3"}, "66": {"name": "Politécnico de Torino"}, "132": {"name": "Universidad de Extremadura"}, "1270": {"name": "BCTEC Ingeniería y Tecnología SpA"}, "545": {"name": "CDP International Perú"}, "447": {"name": "CEAS S.A."}, "9": {"name": "Centro Interamericano de Enseñanza Estadística"}, "28": {"name": "Escuela Normal Superior de Cachan"}, "356": {"name": "Instituto de Fomento Pesquero (IFOP)"}, "159": {"name": "Universidad de Navarra"}, "1296": {"name": "Consultora Ciencia, Educación y Cultura Sustentable Ltda"}, "1234": {"name": "ADN Mentores"}, "308": {"name": "Instituto Nacional de Limnología"}, "340": {"name": "Dirección General del Territorio Marítimo y de Marina Mercante"}, "217": {"name": "Universidad Nacional de Educación a Distancia"}, "198": {"name": "Universidad Federal de Santa Catarina"}, "303": {"name": "Centro de Investigación en Tecnología Aplicada a la Minería"}, "1283": {"name": "Najar Ingenieros SA"}, "563": {"name": "Ministerio de Minería"}, "214": {"name": "Universidad Nacional de Catamarca"}, "138": {"name": "Universidad de Granada"}, "300": {"name": "Washington State University"}, "373": {"name": "Universidade Federal de Minas Gerais (UFMG)"}, "272": {"name": "University of Michigan"}, "165": {"name": "Universidad de Playa Ancha"}, "44": {"name": "Justus Liebig University"}, "122": {"name": "Universidad de Brasilia"}, "51": {"name": "Manhattan College"}, "65": {"name": "Politécnico de Milán"}, "113": {"name": "Universidad de Alicante"}, "500": {"name": "Compañía Minera Antamina"}, "36": {"name": "Ghent University"}, "1305": {"name": "Módulos Wewfe Limitada"}, "258": {"name": "University of Geneva"}, "175": {"name": "Universidad de Tecnologías de Compiegne"}, "319": {"name": "University of New South Wales"}, "421": {"name": "Universidade Estadual de Maringá"}, "1272": {"name": "Compañía Minera Zaldivar Limitada"}, "475": {"name": "Aqualogy Chile"}, "277": {"name": "University of New Mexico"}, "522": {"name": "Johnson Screens"}, "70989": {"name": "Instituto de Investigaciones Agropecuarias (INIA)"}, "338": {"name": "Wabag España"}, "339": {"name": "International Desalination Association"}, "71006": {"name": "CODECITE"}, "1245": {"name": "ChileGlobal Angels"}, "1265": {"name": "Biofiltro Ltda"}, "148": {"name": "Universidad de La Serena"}, "25": {"name": "Escuela Nacional de Puentes y Caminos"}, "57": {"name": "Montpellier SupAgro"}, "62": {"name": "Ohio University"}, "211": {"name": "Universidad Miguel de Cervantes"}, "456": {"name": "LACTEC - Instituto de Pesquisa para o Desenvolvimento"}, "423": {"name": "Pontificia Universidad Javeriana"}, "195": {"name": "Universidad Federal de Minas Gerais"}, "431": {"name": "Universidad de Costa Rica"}, "427": {"name": "Consultor Privado"}, "422": {"name": "Universidade de São Paulo"}, "124": {"name": "Universidad de Cantabria"}, "411": {"name": "Universitat Politècnica de Catalunya"}, "2346": {"name": "Corporación de Desarrollo de Tarapacá"}, "481": {"name": "Universidad Nacional de San Luis"}, "118": {"name": "Universidad de Atacama"}, "354": {"name": "Veolia Water Solutions & Technologies Brasil"}, "267": {"name": "University of Maine"}, "71000": {"name": "Centro de Investigación en Ecosistemas de la Patagonia:"}, "71005": {"name": "Centa Chile"}, "497": {"name": "Sociedad del Canal de Maipo"}, "2369": {"name": "Cowo Puerto Montt"}, "336": {"name": "Cadagua"}, "343": {"name": "Aguas & Procesos S.A."}, "98": {"name": "Universidad Autónoma de Madrid"}, "99": {"name": "Universidad Bernardo O`Higgins"}, "127": {"name": "Universidad de Concepción"}, "115": {"name": "Universidad de Andalucía"}, "86": {"name": "The University of Edinburgh"}, "547": {"name": "Vivest Group Chile"}, "2377": {"name": "Corporación Santiago Innova"}, "530": {"name": "Atacama Agua y Tecnología Ltda."}, "189": {"name": "Universidad del Valle"}, "334": {"name": "Schlumberger Water Services Chile"}, "139": {"name": "Universidad de Grenoble"}, "29": {"name": "Escuela Politecnica Superior Gandia"}, "200": {"name": "Universidad Gabriela Mistral"}, "1303": {"name": "Salitrera Irma Servicios de Higene Ltda"}, "248": {"name": "University of Birmingham"}, "1288": {"name": "Mitica Chiloé E.I.R.L."}, "413": {"name": "Universidad Autónoma de Chapingo"}, "157": {"name": "Universidad de Münster"}, "430": {"name": "Maccaferri De Peru Sac"}, "1298": {"name": "Amphos 21 Consulting Chile Limitada"}, "482": {"name": "Escola Superior de Agricultura “Luiz de Queiroz”"}, "121": {"name": "Universidad de Bolonia"}, "2345": {"name": "Waki Labs"}, "332": {"name": "Omya International AG"}, "63": {"name": "Oregon State University"}, "2374": {"name": "Fundación Colunga"}, "224": {"name": "Universidad Paul Valery Montpellier III"}, "389": {"name": "Universidad Autónoma del Estado de México"}, "64": {"name": "Pennsylvania State University"}, "527": {"name": "Fluor Mining & Metals Chile"}, "1240": {"name": "Mentores x Chile"}, "534": {"name": "Academia Chilena de Ciencias Agronómicas"}, "403": {"name": "Universidad Autónoma de Nuevo León"}, "228": {"name": "Universidad Politécnica de Valencia"}, "192": {"name": "Universidad Estatal de Campinas"}, "282": {"name": "University of Otago"}, "170": {"name": "Universidad de Santiago de Chile"}, "459": {"name": "Asociación CFE-PYPSA-CVA-ICA"}, "8": {"name": "Centro de Investigación Científica y de Educación Superior de Ensenada"}, "76": {"name": "Royal Melbourne Institute of Technology"}, "514": {"name": "Seven Seas Water Corporation"}, "382": {"name": "Universidad Nacional del Litoral"}, "465": {"name": "Universidad de la Costa"}, "2380": {"name": "Fundación Chile"}, "294": {"name": "University of Waterloo"}, "1250": {"name": "Fedefruta"}, "572": {"name": "Gobierno Regional de Antofagasta"}, "288": {"name": "University of Stellenbosch"}, "1293": {"name": "Agroniebla SpA"}, "301": {"name": "York University"}, "391": {"name": "Universidad Nacional de San Juan"}, "491": {"name": "Comité Agua potable rural Liquiñe"}, "188": {"name": "Universidad del Norte"}, "242": {"name": "Universidad Toulouse III"}, "172": {"name": "Universidad de Sevilla"}, "151": {"name": "Universidad de Los Andes"}, "1315": {"name": "JRI Ingeniería SA"}, "467": {"name": "Universidad de Carabobo"}, "404": {"name": "Universidad Nacional de Santiago del Estero"}, "460": {"name": "Universidad Pontificia Bolivariana"}, "168": {"name": "Universidad de Saarland"}, "2355": {"name": "Co-WorkLATAM Monjitas"}, "71001": {"name": "Agrícola Centro de Evaluación Rosario Ltda"}, "304": {"name": "Ministerio de Obras Públicas"}, "2354": {"name": "Co-Work Santiago Centro"}, "155": {"name": "Universidad de Milan-Bicocca"}, "395": {"name": "Universidad de Los Andes Venezuela"}, "70994": {"name": "CORFO INNOVA"}, "220": {"name": "Universidad Paris Dauphine - Paris IX"}, "229": {"name": "Universidad Rey Juan Carlos"}, "2371": {"name": "Asociación por el desarrollo Paralelo 47"}, "33": {"name": "Florida State University"}, "432": {"name": "Instituto Tecnológico y de Estudios Superiores de Monterrey"}, "199": {"name": "Universidad Finis Terrae"}, "329": {"name": "Comisión Chilena del Cobre"}, "72": {"name": "Rachel Carson Center"}, "517": {"name": "Hazen Research Inc."}, "393": {"name": "Inesproc S.A."}, "70997": {"name": "Centro de Estudios Avanzados en Zonas Áridas"}, "2357": {"name": "Duam S.A."}, "476": {"name": "Obras Sanitarias del Estado"}, "455": {"name": "Universidad Manuela Beltrán"}, "52": {"name": "Massachusetts Institute of Technology"}, "483": {"name": "Ministerio de Agricultura"}, "558": {"name": "Centro de Investigación en Ecosistemas de la Patagonia"}, "289": {"name": "University of Strathclyde"}, "262": {"name": "University of Konstanz"}, "370": {"name": "SENSUS Chile S.A."}, "221": {"name": "Universidad París I"}, "102": {"name": "Universidad Católica de Córdoba"}, "369": {"name": "Aguas Antofagasta"}, "31": {"name": "Escuela Técnica de Praga"}, "521": {"name": "Anglo American Chile"}, "147": {"name": "Universidad de La Habana"}, "360": {"name": "Museo de Historia Natural de Buenos Aires"}, "562": {"name": "Ministerio de Energía"}, "1261": {"name": "Instituo de Campos de Hielo"}, "137": {"name": "Universidad de Göttingen"}, "243": {"name": "Université Laval"}, "299": {"name": "Wageningen University"}, "194": {"name": "Universidad Europea de Madrid"}, "513": {"name": "Walsh Perú"}, "539": {"name": "Comisión Nacional de Riego"}, "47": {"name": "Leland Stanford Junior University"}, "237": {"name": "Universidad Técnica de Lublin"}, "1258": {"name": "Agrosat S.A."}, "16": {"name": "Columbia University"}, "1289": {"name": "Go Patagonia SpA"}, "1254": {"name": "Asociación de Canalistas del Maule"}, "337": {"name": "LG Nano H2O"}, "350": {"name": "Geohidrología Consultores"}, "1287": {"name": "Aguaex (incluido x mi, no aparece en Corfo)"}, "1271": {"name": "Corporación Nacional del Cobre de Chile"}, "442": {"name": "Universidad Santo Tomas Seccional Tunja"}, "493": {"name": "Ética en los Bosques"}, "1280": {"name": "Soluciones Mecánicas Mechsol Limitada"}, "23": {"name": "Escuela Europea de Negocios"}, "268": {"name": "University of Manchester"}, "54": {"name": "Mississippi State University"}, "193": {"name": "Universidad Estatal de Suslov"}, "27": {"name": "Escuela Nacional Superior de Electrónica, Electrotécnica, Informática, Hidráulica y Telecomunicaciones"}, "1297": {"name": "Alister Ingeniería y Construcción Limitada"}, "1314": {"name": "Iansagro SA"}, "167": {"name": "Universidad de Roma II"}, "107": {"name": "Universidad Católica del Norte"}, "162": {"name": "Universidad de París XI"}, "312": {"name": "University of the Witwatersrand"}, "2350": {"name": "Cowork Balmaceda Arte Joven"}, "330": {"name": "MWH USA"}, "367": {"name": "Aguas Andinas"}, "426": {"name": "Intertechne"}, "2381": {"name": "Mujeres Empresarias"}, "43": {"name": "Instituto Tecnológico de Israel"}, "321": {"name": "Zdoor bv"}, "479": {"name": "Universidad Nacional de Río Claro"}, "450": {"name": "Universidad Autónoma Metropolitana-Iztapalapa"}, "457": {"name": "Universidad de Castilla - La Mancha"}, "494": {"name": "Parés y Álvarez Ingenieros Asociados Ltda"}, "1235": {"name": "MentorInn"}, "365": {"name": "Coopagua Santo Domingo Ltda."}, "280": {"name": "University of Notre Dame"}, "238": {"name": "Universidad Técnica de München"}, "2378": {"name": "Universidad Tecnológica de Chile"}, "551": {"name": "EDIC Ingenieros"}, "143": {"name": "Universidad de Hokkaido"}, "390": {"name": "Siam S.A."}, "20": {"name": "Erasmus University Rotterdam"}, "567": {"name": "Teck Chile"}, "190": {"name": "Universidad Diego Portales"}, "351": {"name": "Valoriza Agua"}, "152": {"name": "Universidad de Los Lagos"}, "1308": {"name": "Empresa de Ingeniería Valtec y Compañía Limitada"}, "286": {"name": "University of Southampton"}, "166": {"name": "Universidad de Rennes II Alta Bretaña"}, "322": {"name": "Veolia Water Solutions & Technologies Francia"}, "186": {"name": "Universidad del Desarrollo"}, "345": {"name": "Esmeralda Corp. SAC"}, "1273": {"name": "Ingeniería Gestión y Desarrollo SA"}, "38": {"name": "Imperial College London"}, "357": {"name": "Centro de Investigación en Ecosistemas de la Patagonia"}, "342": {"name": "Jacobs Australia"}, "93": {"name": "Universidad Arturo Prat"}, "257": {"name": "University of East Anglia"}, "463": {"name": "Universidade Federal de Goiás"}, "504": {"name": "International Council on Mining and Metals"}, "273": {"name": "University of Minnesota"}, "112": {"name": "Universidad de Alcalá de Henares"}, "398": {"name": "Universidade Estadual de Campinas (UNICAMP)"}, "191": {"name": "Universidad Espíritu Santo de Guayaquil"}, "219": {"name": "Universidad Nacional del Sur"}, "205": {"name": "Universidad Libre de Berlín"}, "246": {"name": "University of Antwerp"}, "83": {"name": "The American University"}, "2353": {"name": "La Makinita Cowork"}, "1304": {"name": "Confinger SpA"}, "97": {"name": "Universidad Autónoma de Chile"}, "1263": {"name": "BakerPatagonia"}, "91": {"name": "Universidad Aplicada de Aquisgrán"}, "555": {"name": "Armada de Chile"}, "311": {"name": "Universidad de Tarapacá"}, "410": {"name": "Universidade Federal do Paraná"}, "325": {"name": "Southern Peru Copper Corp"}, "2375": {"name": "Hub Salud Concepción"}, "158": {"name": "Universidad de Nápoles Federico II"}, "109": {"name": "Universidad Central de Chile"}, "154": {"name": "Universidad de Málaga"}, "79": {"name": "Stanford University"}, "22": {"name": "Escuela de Minas de ParisTech"}, "174": {"name": "Universidad de Talca"}, "388": {"name": "Secretaría de Educación Superior, Ciencia, Tecnología e Innovación"}, "70": {"name": "Queen’s University Kingston"}, "359": {"name": "Museo de Historia Natural de Paris"}, "1356": {"name": "Chrysalis"}, "515": {"name": "Teck Resources Chile"}, "546": {"name": "Ecometers S.A."}, "80": {"name": "State University of New York"}, "5": {"name": "Carnegie Mellon University"}, "156": {"name": "Universidad de Montpellier"}, "438": {"name": "Universidad Autónoma de Manizales"}, "270": {"name": "University of Massachusetts"}, "1253": {"name": "Inversiones Oro Azul Limitada"}, "1269": {"name": "Tratamientos de agua Manatial Chile SA"}, "402": {"name": "Universidad Centroccidental \"Lisandro Alvarado\" (UCLA)"}, "407": {"name": "GOTTA Ingeniería S.A.S."}, "310": {"name": "Modelación Ambiental SpA"}, "275": {"name": "University of Nebraska"}, "379": {"name": "Universidad de la República"}, "140": {"name": "Universidad de Guadalajara"}, "349": {"name": "Abengoa"}, "1251": {"name": "Fundación Centro de Los Bosques Nativos FORECOS"}, "187": {"name": "Universidad del Mar"}, "2358": {"name": "Innova Cowork"}, "182": {"name": "Universidad de Wurzburg"}, "1242": {"name": "3IE"}, "376": {"name": "Tohoku University"}, "234": {"name": "Universidad Técnica de Braunschweig"}, "181": {"name": "Universidad de Viña del Mar"}, "508": {"name": "Ausenco Vector Argentina"}, "1247": {"name": "Red de Capitalistas Ángeles Fen Ventures"}, "77": {"name": "RWTH Aachen University"}, "2356": {"name": "Cowork Radicales"}, "136": {"name": "Universidad de Gotemburgo"}, "48": {"name": "London Metropolitan University"}, "1295": {"name": "Maestranza Diesel S.A."}, "34": {"name": "Fundación Centro Internacional de Hidrología Subterránea, Barcelona"}, "12": {"name": "Centro Nacional de Estudios Espaciales"}, "4": {"name": "Aston University"}, "1284": {"name": "DVS Tecnología SA"}, "386": {"name": "Universidad Michoacana de San Nicolás de Hidalgo"}, "225": {"name": "Universidad Pierre Mendès France"}, "305": {"name": "National Research Institute of Science and Technology for Environment and Agriculture"}, "249": {"name": "University of Bristol"}, "41": {"name": "Instituto de Investigaciones Ecológica de Málaga"}, "399": {"name": "Universidade Positivo"}, "293": {"name": "University of Washington"}, "1249": {"name": "Fundación Chile"}, "185": {"name": "Universidad del Cauca"}, "149": {"name": "Universidad de Leipzig"}, "1274": {"name": "Marpro Chile SA"}, "396": {"name": "Universidad Nacional de La Plata"}, "448": {"name": "Hidrocaminos S. A."}, "259": {"name": "University of Göttingen"}, "1266": {"name": "Posada del Parque"}, "557": {"name": "Centro de Ecología Aplicada"}, "425": {"name": "Gobierno Autónomo Descentralizado Provincia de Pichincha"}, "244": {"name": "University College"}, "437": {"name": "Escuela Superior Politécnica del Litoral"}, "142": {"name": "Universidad de Hannover"}, "307": {"name": "Minería & Servicios Chile"}, "543": {"name": "Servicio de Impuestos Internos"}, "100": {"name": "Universidad Blaise Pascal, Clermont-Ferrand"}, "458": {"name": "Pontificia Universidad Católica del Perú"}, "486": {"name": "Programa Eco - Región Agenda Local 21"}, "478": {"name": "GeoBioForesta"}, "1246": {"name": "Creación Red de Inversionistas Ángeles: Santiago"}, "509": {"name": "Fundación Chile"}, "487": {"name": "Ministerio de Medio Ambiente"}, "55": {"name": "Missouri University – Rolla"}, "233": {"name": "Universidad Técnica de Berlín"}, "394": {"name": "Universidad Autónoma de Querétaro"}, "453": {"name": "Universidad Nacional Experimental Francisco de Miranda"}, "2382": {"name": "TechnoServe Inc."}, "1248": {"name": "Dad Neos"}, "492": {"name": "Bioforest S.A."}, "435": {"name": "Universidad Tecnológica de Pereira"}, "256": {"name": "University of Colorado"}, "82": {"name": "Tecnológico de Monterrey"}, "37": {"name": "ILPES-CEPAL"}, "512": {"name": "Hatch Perú"}, "99087": {"name": "Universidad del Pacífico"}, "538": {"name": "Centro de Desenvolvimento da Tecnologia Nuclear"}, "524": {"name": "WorleyParsons Canadá"}, "58": {"name": "New York University"}, "146": {"name": "Universidad de La Frontera"}, "2456": {"name": "Magical Startups"}, "433": {"name": "Universidad Nacional de Chimborazo"}, "401": {"name": "Universidad Nacional de Cajamarca"}, "204": {"name": "Universidad La República"}, "381": {"name": "Universidad Nacional de Ingeniería"}, "326": {"name": "Compañía de Minas Buenaventura S.A.A."}, "2347": {"name": "Opendat"}, "2368": {"name": "Patagonia Labspace"}, "114": {"name": "Universidad de Almería"}, "525": {"name": "Xstrata Copper Chile"}, "179": {"name": "Universidad de Valparaíso"}, "56": {"name": "Monash University"}, "126": {"name": "Universidad de Ciencias Aplicadas de Leipzig"}, "519": {"name": "Anglo American Sudáfrica"}, "207": {"name": "Universidad Ludwig Maximilian"}, "454": {"name": "University of Alaska Fairbanks"}, "24": {"name": "Escuela Nacional de Aeronáutica y Mecánica (ENSMA)"}, "120": {"name": "Universidad de Berna"}, "129": {"name": "Universidad de Cristian Albrechts de Kiel"}, "61": {"name": "Ohio State University"}, "324": {"name": "Corporación Nacional del Cobre"}, "452": {"name": "Asociación Colombiana de Hidrogeólogos"}, "3": {"name": "Arizona State University"}, "502": {"name": "CSIRO Process Science and Engineering"}, "364": {"name": "Carlos Rivas Padilla y Cía. Ltda."}, "32": {"name": "Facultad Latinoamericana de Ciencias Sociales (FLACSO)"}, "327": {"name": "MWH Chile"}, "323": {"name": "SRK Consulting Chile"}, "1309": {"name": "Empresa Nacional de Electricidad S.A"}, "318": {"name": "Doosan Enpure Ltd"}, "1294": {"name": "Proter S.A."}, "50": {"name": "Ludwig-Maximilians-Universität München"}, "495": {"name": "Independiente"}, "371": {"name": "Instituto de Botânica"}, "444": {"name": "Ingenieria 75"}, "2361": {"name": "Fundación Novo Milenio"}, "368": {"name": "Aguas del Altiplano S.A."}, "698": {"name": "Instituto del Medio Ambiente (IDMA)"}, "387": {"name": "Logist Geoplan"}, "531": {"name": "Pall Corporation USA"}, "2": {"name": "AgroParis Tech, Escuela Doctoral ABIES"}, "116": {"name": "Universidad de Antofagasta"}, "544": {"name": "Asociación Gremial de Servicios de Agua Potable Rural"}, "1252": {"name": "La Cumbre Baguales"}, "554": {"name": "Antofagasta Minerals"}, "253": {"name": "University of Canterbury"}, "1278": {"name": "Pigmentos Naturales SA"}, "2379": {"name": "ONG Acción Emprendedora"}, "443": {"name": "Universidad Nacional de La Pampa"}, "290": {"name": "University of Tennessee"}, "2349": {"name": "Housenovo Cowork"}, "70991": {"name": "Fundación CSIRO Chile"}, "15": {"name": "Colorado State University"}, "537": {"name": "CoandaScreen"}, "533": {"name": "Maptek"}, "208": {"name": "Universidad Mayor de San Andrés"}, "160": {"name": "Universidad de Orleáns"}, "2372": {"name": "Nomadesk"}, "278": {"name": "University of Newcastle"}, "215": {"name": "Universidad Nacional de Colombia"}, "106": {"name": "Universidad Católica del Maule"}, "355": {"name": "MWH Australia"}, "74": {"name": "Rensselaer Polytechnic Institute"}, "94": {"name": "Universidad Austral de Chile"}, "516": {"name": "Alden Research Laboratory Inc."}, "348": {"name": "Jacobs New Zealand"}, "1260": {"name": "Aquainnovo"}, "511": {"name": "MWH Peru"}, "276": {"name": "University of Nevada, Reno"}, "347": {"name": "Caribbean Desalination Association (CaribDA)"}, "163": {"name": "Universidad de Pisa"}, "49": {"name": "Loughborough University"}, "6": {"name": "Centro Agronómico Tropical de Investigación y Enseñanza"}, "283": {"name": "University of Oxford"}, "75": {"name": "Royal Institute of Technology"}, "1241": {"name": "Net Mentora"}, "70992": {"name": "Fundación para el Desarrollo Frutícola"}, "1237": {"name": "Endeavor"}, "60": {"name": "Northwestern University"}, "14": {"name": "Coastal Engineering and Port Development, UNESCO IHE- Delft"}, "239": {"name": "Universidad Técnica del Estado"}, "380": {"name": "Universidad Distrital Francisco José de Caldas"}, "470": {"name": "Universidad Católica Andrés Bello"}, "119": {"name": "Universidad de Barcelona"}, "451": {"name": "Universidad Autónoma de Yucatán"}, "302": {"name": "Universidad de Murcia"}, "145": {"name": "Universidad de Kyoto"}, "1307": {"name": "Rafael Sotomayor y Compañía Limitada"}, "240": {"name": "Universidad Técnica Federico Santa María"}, "206": {"name": "Universidad Libre de Bruselas"}, "341": {"name": "Pentair Water Latin America"}, "1238": {"name": "Maas Latam"}, "1244": {"name": "Plataforma Electrónica de Inversión"}, "197": {"name": "Universidad Federal de Río de Janeiro"}, "414": {"name": "Geoambiente SRL"}, "2383": {"name": "Microsoft Chile"}, "176": {"name": "Universidad de Toulouse II-Le Mirail"}, "59": {"name": "North Carolina State University"}, "568": {"name": "Terra Remote Sensing Ltda."}, "254": {"name": "University of Chicago"}, "823727": {"name": "Advanced Mining Technology Center"}, "2370": {"name": "La Minga Cowork"}, "177": {"name": "Universidad de Trento"}, "21": {"name": "Escuela de estudios superiores y postgrado en Madrid"}, "385": {"name": "Empresa"}, "462": {"name": "Sociedad Minera Cerro Verde SAA"}, "70993": {"name": "Fundación Wageningen UR Chil"}, "17": {"name": "Cornell University"}, "226": {"name": "Universidad Politécnica de Cataluña"}, "496": {"name": "Empresa Nacional de Electricidad"}, "19": {"name": "Delft University of Technology"}, "183": {"name": "Universidad de Zaragoza"}, "7865": {"name": "Universidad de Aconcagua"}, "2360": {"name": "Urban Station"}, "70996": {"name": "CONICYT"}, "2352": {"name": "Cidi Lab"}, "71002": {"name": "Centro de Investigacón Minera y Metalúrgica"}, "2348": {"name": "La Brújula Cowork"}, "130": {"name": "Universidad de Deusto, Bilbao"}, "548": {"name": "Emaresa S.A."}, "252": {"name": "University of Cambridge"}, "81": {"name": "Swedish University of Agricultural Sciences"}, "408": {"name": "Universidad Nacional del Centro de la Provincia de Buenos Aires"}, "397": {"name": "Servicios Hidrogeologicos Integrales"}, "90": {"name": "Universidad Alberto Hurtado"}, "70999": {"name": "Fundación para la Innovación Agraria (FIA)"}, "70995": {"name": "CORFO"}, "315": {"name": "Deltares"}, "235": {"name": "Universidad Técnica de Darmstadt"}, "477": {"name": "Consultor Forestal"}, "2365": {"name": "La Nube Valdivia"}, "1300": {"name": "Cooperativa Agrícola Control Pisquero de Elqui y Limarí Ltda"}, "392": {"name": "Universidade Estadual Paulista Júlio de Mesquita Filho (UNESP)"}, "441": {"name": "Universidad de Antioquia"}, "484": {"name": "Iniciativa Agua y Medio Ambiente"}, "439": {"name": "Universidad Autónoma de Chiapas"}, "1282": {"name": "Plasticopper SpA"}, "1277": {"name": "Ingeniería y Construcciones Salas Hermanos Ltda"}, "560": {"name": "Dirección General de Aeronáutica Civil"}, "2364": {"name": "Kowork Temuco"}, "222": {"name": "Universidad París II"}, "464": {"name": "Estudios y Asesorías Ingenieros Ltda."}, "346": {"name": "Klohn Crippen Berger"}, "265": {"name": "University of Liverpool"}, "306": {"name": "GP Consultores Ltda."}, "474": {"name": "Leopold Xylem Water Solutions"}, "173": {"name": "Universidad de Stuttgart"}, "261": {"name": "University of Illinois at Urbana-Champaign"}, "428": {"name": "Universidad Técnica Particular de Loja"}, "363": {"name": "Instituto Federal de Educação, Ciência e Tecnologia do Tocantins"}, "297": {"name": "Vilnius University"}, "1310": {"name": "Sacyr Chile S.A."}, "70998": {"name": "Centro de Estudios del Cuaternario de Fuego-Patagonia y Antártica"}, "245": {"name": "University for Peace, Human Rights Centre"}, "184": {"name": "Universidad del Bío Bío"}, "372": {"name": "Environment Canada"}, "529": {"name": "WorleyParsons Australia"}, "202": {"name": "Universidad Iberoamericana"}, "503": {"name": "Everis Energy Services (EXELERIA)"}, "333": {"name": "Pall Corporation UK"}, "69": {"name": "Pontificia Universidad Católica de Valparaíso"}, "374": {"name": "Universidade Federal do Rio Grande do Sul"}, "461": {"name": "Universidad de Lisboa"}, "535": {"name": "Arquitectura & Energía"}, "419": {"name": "Consejo Nacional de Ciencia y Tecnología (Conacyt)"}, "485": {"name": "Forestal Mininco"}, "1259": {"name": "Agua Glaciar S.A."}, "417": {"name": "Universidad Nacional Agraria La Molina (UNALM)"}, "361": {"name": "Andalué Ambiental Ltda."}, "1239": {"name": "Red de Mentores Norte"}, "134": {"name": "Universidad de Gales"}, "212": {"name": "Universidad Nacional Agraria La Molina"}, "445": {"name": "Universidad Juárez Autónoma de Tabasco"}, "150": {"name": "Universidad de Lleida"}, "271": {"name": "University of Melbourne"}, "1279": {"name": "Ecopreneur SA"}, "1": {"name": "Academia Politécnica Naval"}, "449": {"name": "Universidad EAFIT"}, "266": {"name": "University of London"}, "104": {"name": "Universidad Católica de Temuco"}, "26": {"name": "Escuela Nacional Superior Agronómica de Montpellier"}, "263": {"name": "University of Leeds"}, "274": {"name": "University of Montana"}, "216": {"name": "Universidad Nacional de Córdoba"}, "468": {"name": "Centro Interamericano de Recursos del Agua"}, "296": {"name": "University of Wisconsin, Madison"}, "2376": {"name": "Corporación para el Desarrollo de la Innovación y el Emprendimiento de la Región de Antofagasta"}, "1299": {"name": "Donoso & Bouillet Consultores Limitada"}, "335": {"name": "Abeinsa Abengoa"}, "18": {"name": "Czech University of Agriculture"}, "344": {"name": "Unidad minera Cerro Lindo, Compañía Minera Milpo"}, "1281": {"name": "E.CL SA"}, "1268": {"name": "Biodiversa SA"}, "506": {"name": "Cerro Vanguardia S.A."}, "210": {"name": "Universidad Metropolitana de Ciencias de la Educación"}, "110": {"name": "Universidad Central Marta Abreus de Las Villas"}, "1286": {"name": "Cooperativa de Trabajo Agua de la Montaña"}, "144": {"name": "Universidad de Huelva"}, "1302": {"name": "Aguas Chañar SA"}, "40": {"name": "Instituto de Hidrología de Madrid"}, "295": {"name": "University of Winnipeg"}, "1257": {"name": "Comunidad de Aguas del Canal Chufquen"}, "1291": {"name": "Fresh Water"}, "117": {"name": "Universidad de Artes y Ciencias Sociales ARCIS"}, "409": {"name": "Universidad de California, Davis"}, "536": {"name": "Watersavr™ Flexible Solutions Ltd."}, "13": {"name": "Clausthal University of Technology"}, "2351": {"name": "Fábrica de Medios"}, "1312": {"name": "Livn"}, "131": {"name": "Universidad de Erlangen-Nürnberg"}, "101": {"name": "Universidad Carlos III"}, "2373": {"name": "iF Fábrica de Ideas"}, "213": {"name": "Universidad Nacional Andrés Bello"}, "284": {"name": "University of Queensland"}, "542": {"name": "Universidad Andrés Bello"}, "317": {"name": "Votorantim Metais"}, "169": {"name": "Universidad de Salamanca"}, "1255": {"name": "Essbio SA"}, "135": {"name": "Universidad de Gerona"}, "358": {"name": "Universidad Mayor de San Simón"}, "1275": {"name": "Aguamarina SPA"}}}